py_tor_runner-1.0.1.dist-info/licenses/LICENSE
tor/__init__.py
tor/proxy.py
py_tor_runner-1.0.1.dist-info/METADATA
py_tor_runner-1.0.1.dist-info/WHEEL
py_tor_runner-1.0.1.dist-info/top_level.txt
py_tor_runner-1.0.1.dist-info/RECORD
