Metadata-Version: 2.4
Name: py-tor-runner
Version: 1.0.1
Summary: A Python utility for managing Tor processes to enable anonymous web browsing through SOCKS5 proxies.
Author: Tobias Würth
License-Expression: Unlicense
Project-URL: Repository, https://github.com/tobiaswuerth/tor-runner
Project-URL: Bug Tracker, https://github.com/tobiaswuerth/tor-runner/issues
Keywords: python,tor,proxy,SOCKS5
Classifier: Programming Language :: Python :: 3
Classifier: Operating System :: OS Independent
Requires-Python: >=3.9
License-File: LICENSE
Dynamic: license-file
